{
  "project_info": {
    "project_number": "549528655351",
    "project_id": "eaproyecto-ff8ba",
    "storage_bucket": "eaproyecto-ff8ba.appspot.com"
  },
  "client": [
    {
      "client_info": {
        "mobilesdk_app_id": "1:549528655351:android:a282a44b59da113f690af2",
        "android_client_info": {
          "package_name": "com.myproject"
        }
      },
      "oauth_client": [
        {
          "client_id": "549528655351-0lmsa6u9fgdh1d75sp52chhcvj54mhd6.apps.googleusercontent.com",
          "client_type": 3
        }
      ],
      "api_key": [
        {
          "current_key": "AIzaSyCtuyp4Yk4PVKiGWS7SmIvB57ZJmMIph90"
        }
      ],
      "services": {
        "appinvite_service": {
          "other_platform_oauth_client": [
            {
              "client_id": "549528655351-0lmsa6u9fgdh1d75sp52chhcvj54mhd6.apps.googleusercontent.com",
              "client_type": 3
            }
          ]
        }
      }
    }
  ],
  "configuration_version": "1"
}